exo_graph/__init__.py
exo_graph/document_processor.py
exo_graph/config/__init__.py
exo_graph/config/neo4j_config.py
exo_graph/config/neo4j_schema.py
exo_graph/core/__init__.py
exo_graph/core/engine.py
exo_graph/llm/__init__.py
exo_graph/llm/llm_client_factory.py
exo_graph/llm/llm_config.py
exo_graph/llm/llm_interface.py
exo_graph/models/__init__.py
exo_graph/models/classifier_map.py
exo_graph/models/models.py
exo_graph/storage/__init__.py
exo_graph/storage/graph_db.py
exo_graph/utils/__init__.py
exo_graph/utils/date_parser.py
exo_graph/utils/edge_name_utils.py
exo_graph/utils/encoders.py
exo_graph/utils/graph_standardizer.py
exo_graph/utils/neo4j_index_manager.py
llm_exo_graph-1.2.1.dist-info/METADATA
llm_exo_graph-1.2.1.dist-info/WHEEL
llm_exo_graph-1.2.1.dist-info/RECORD
