Metadata-Version: 2.4
Name: llm-exo-graph
Version: 1.2.1
Summary: Advanced Knowledge Graph Engine with Document Processing, Semantic Search and Multi-LLM Integration
Project-URL: Homepage, https://github.com/dasein108/llm-exo-graph
Project-URL: Repository, https://github.com/dasein108/llm-exo-graph.git
Project-URL: Issues, https://github.com/dasein108/llm-exo-graph/issues
Project-URL: Documentation, https://github.com/dasein108/llm-exo-graph/docs
Project-URL: Source, https://github.com/dasein108/llm-exo-graph/
Author-email: Maksims Gavrilovs <acidpictures@gmail.com>
Keywords: ai,conflict-resolution,entity-recognition,graph-database,hybrid-search,information-extraction,knowledge-graph,llm,machine-learning,neo4j,nlp,openai,relationship-extraction,semantic-search,temporal-tracking,vector-search
Classifier: Development Status :: 4 - Beta
Classifier: Intended Audience :: Developers
Classifier: Intended Audience :: Science/Research
Classifier: License :: OSI Approved :: MIT License
Classifier: Operating System :: OS Independent
Classifier: Programming Language :: Python :: 3
Classifier: Programming Language :: Python :: 3.10
Classifier: Programming Language :: Python :: 3.11
Classifier: Programming Language :: Python :: 3.12
Classifier: Topic :: Database
Classifier: Topic :: Scientific/Engineering :: Artificial Intelligence
Classifier: Topic :: Software Development :: Libraries :: Python Modules
Classifier: Topic :: Text Processing :: Linguistic
Requires-Python: >=3.10
Requires-Dist: dateparser>=1.1.0
Requires-Dist: json-repair>=0.44.0
Requires-Dist: neo4j>=5.0.0
Requires-Dist: numpy>=1.21.0
Requires-Dist: openai>=1.0.0
Requires-Dist: python-dotenv>=0.19.0
Requires-Dist: scikit-learn>=1.0.0
Requires-Dist: scipy>=1.7.0
Requires-Dist: sentence-transformers>=2.2.0
Provides-Extra: all
Requires-Dist: black>=22.0.0; extra == 'all'
Requires-Dist: fastapi>=0.104.0; extra == 'all'
Requires-Dist: flake8>=5.0.0; extra == 'all'
Requires-Dist: langchain-community>=0.3.27; extra == 'all'
Requires-Dist: langchain>=0.0.350; extra == 'all'
Requires-Dist: mkdocs-material>=9.0.0; extra == 'all'
Requires-Dist: mkdocs>=1.5.0; extra == 'all'
Requires-Dist: mypy>=0.991; extra == 'all'
Requires-Dist: pre-commit>=2.20.0; extra == 'all'
Requires-Dist: pydantic>=2.0.0; extra == 'all'
Requires-Dist: pypdf>=3.17.0; extra == 'all'
Requires-Dist: pytest-cov>=4.0.0; extra == 'all'
Requires-Dist: pytest>=7.0.0; extra == 'all'
Requires-Dist: unstructured==0.18.11; extra == 'all'
Requires-Dist: uvicorn>=0.24.0; extra == 'all'
Provides-Extra: api
Requires-Dist: fastapi>=0.104.0; extra == 'api'
Requires-Dist: pydantic>=2.0.0; extra == 'api'
Requires-Dist: uvicorn>=0.24.0; extra == 'api'
Provides-Extra: dev
Requires-Dist: black>=22.0.0; extra == 'dev'
Requires-Dist: flake8>=5.0.0; extra == 'dev'
Requires-Dist: mypy>=0.991; extra == 'dev'
Requires-Dist: pre-commit>=2.20.0; extra == 'dev'
Requires-Dist: pytest-cov>=4.0.0; extra == 'dev'
Requires-Dist: pytest>=7.0.0; extra == 'dev'
Provides-Extra: documents
Requires-Dist: langchain-community>=0.3.27; extra == 'documents'
Requires-Dist: langchain>=0.0.350; extra == 'documents'
Requires-Dist: pypdf>=3.17.0; extra == 'documents'
Requires-Dist: unstructured==0.18.11; extra == 'documents'
